quasiqueue/__init__.py
quasiqueue/_version.py
quasiqueue/builder.py
quasiqueue/cli.py
quasiqueue/py.typed
quasiqueue/reader.py
quasiqueue/runner.py
quasiqueue/settings.py
tests/__init__.py
tests/test_quasiqueue.py
tests/test_settings.py
tests/utils.py
quasiqueue-0.5.0.dist-info/LICENSE
quasiqueue-0.5.0.dist-info/METADATA
quasiqueue-0.5.0.dist-info/WHEEL
quasiqueue-0.5.0.dist-info/entry_points.txt
quasiqueue-0.5.0.dist-info/top_level.txt
quasiqueue-0.5.0.dist-info/RECORD
