Metadata-Version: 2.1
Name: quasiqueue
Version: 0.5.0
Summary: A Simple High Performance Multiprocess Queue
Author: Robert Hafner
License: MIT License
Requires-Python: >=3.10
License-File: LICENSE
Requires-Dist: psutil
Requires-Dist: pydantic~=2.0
Requires-Dist: pydantic-settings
Requires-Dist: typer>=0.9.0
Provides-Extra: dev
Requires-Dist: build; extra == "dev"
Requires-Dist: dapperdata; extra == "dev"
Requires-Dist: glom; extra == "dev"
Requires-Dist: mypy; extra == "dev"
Requires-Dist: pytest; extra == "dev"
Requires-Dist: pytest-asyncio; extra == "dev"
Requires-Dist: pytest-cov; extra == "dev"
Requires-Dist: pytest-pretty; extra == "dev"
Requires-Dist: ruamel.yaml; extra == "dev"
Requires-Dist: ruff; extra == "dev"
Requires-Dist: toml-sort; extra == "dev"
Requires-Dist: types-psutil; extra == "dev"
